{
    "products": [
        {
            "images": ["images/products/ABRotWeiß_1jpg", "images/products/ABRotWeiß_2.jpg", "images/products/ABRotWeiß_3.jpg", "images/products/ABRotWeiß_4.jpg"],
            "artnr": "A001",
            "name": "Stoffarmband",
            "color": "rot-weiß",
            "price": 19.99
        },
        {
            "images": ["images/products/ABSchwarz_1.jpg", "images/products/ABSchwarz_2.jpg", "images/products/ABSchwarz_3.jpg", "images/products/ABSchwarz_4.jpg"],
            "artnr": "A002",
            "name": "Stoffarmband",
            "color": "schwarz",
            "price": 19.99
        }
    ]
}